open_detection/__init__.py
open_detection/anchor.py
open_detection/dataset/__init__.py
open_detection/dataset/coco.py
open_detection/dataset/parallel.py
open_detection-0.2.2.dist-info/LICENSE
open_detection-0.2.2.dist-info/METADATA
open_detection-0.2.2.dist-info/WHEEL
open_detection-0.2.2.dist-info/top_level.txt
open_detection-0.2.2.dist-info/RECORD
